dflow_galaxy/__init__.py
dflow_galaxy/app/__init__.py
dflow_galaxy/app/common.py
dflow_galaxy/app/cp2k_lightning/__init__.py
dflow_galaxy/app/cp2k_lightning/dflow.py
dflow_galaxy/app/cp2k_lightning/main.py
dflow_galaxy/app/dynacat_md/__init__.py
dflow_galaxy/app/dynacat_md/dflow.py
dflow_galaxy/app/dynacat_md/main.py
dflow_galaxy/app/dynacat_md/report.py
dflow_galaxy/app/dynacat_tesla/__init__.py
dflow_galaxy/app/dynacat_tesla/main.py
dflow_galaxy/app/dynacat_tesla/report.py
dflow_galaxy/core/__init__.py
dflow_galaxy/core/dflow_builder.py
dflow_galaxy/core/dispatcher.py
dflow_galaxy/core/log.py
dflow_galaxy/core/pydantic.py
dflow_galaxy/core/types.py
dflow_galaxy/core/util.py
dflow_galaxy/main.py
dflow_galaxy/res/__init__.py
dflow_galaxy/res/cp2k_data/ALL_BASIS_SETS
dflow_galaxy/res/cp2k_data/ALL_POTENTIALS
dflow_galaxy/res/cp2k_data/AcPP1_POTENTIALS
dflow_galaxy/res/cp2k_data/BASIS_ADMM
dflow_galaxy/res/cp2k_data/BASIS_ADMM_MOLOPT
dflow_galaxy/res/cp2k_data/BASIS_ADMM_UZH
dflow_galaxy/res/cp2k_data/BASIS_ADMM_ae
dflow_galaxy/res/cp2k_data/BASIS_LRIGPW_AUXMOLOPT
dflow_galaxy/res/cp2k_data/BASIS_MINBAS
dflow_galaxy/res/cp2k_data/BASIS_MINIX
dflow_galaxy/res/cp2k_data/BASIS_MOLOPT
dflow_galaxy/res/cp2k_data/BASIS_MOLOPT_AcPP1
dflow_galaxy/res/cp2k_data/BASIS_MOLOPT_LnPP1
dflow_galaxy/res/cp2k_data/BASIS_MOLOPT_LnPP2
dflow_galaxy/res/cp2k_data/BASIS_MOLOPT_UCL
dflow_galaxy/res/cp2k_data/BASIS_MOLOPT_UZH
dflow_galaxy/res/cp2k_data/BASIS_PERIODIC_GW
dflow_galaxy/res/cp2k_data/BASIS_RI_cc-TZ
dflow_galaxy/res/cp2k_data/BASIS_SET
dflow_galaxy/res/cp2k_data/BASIS_ZIJLSTRA
dflow_galaxy/res/cp2k_data/BASIS_ccGRB_UZH
dflow_galaxy/res/cp2k_data/BASIS_def2_QZVP_RI_ALL
dflow_galaxy/res/cp2k_data/BASIS_pob
dflow_galaxy/res/cp2k_data/ECP_POTENTIALS
dflow_galaxy/res/cp2k_data/ECP_POTENTIALS_pob-TZVP-rev2
dflow_galaxy/res/cp2k_data/EMSL_BASIS_SETS
dflow_galaxy/res/cp2k_data/GTH_BASIS_SETS
dflow_galaxy/res/cp2k_data/GTH_POTENTIALS
dflow_galaxy/res/cp2k_data/GTH_SOC_POTENTIALS
dflow_galaxy-0.1.9.dist-info/LICENSE
dflow_galaxy-0.1.9.dist-info/METADATA
dflow_galaxy-0.1.9.dist-info/WHEEL
dflow_galaxy-0.1.9.dist-info/entry_points.txt
dflow_galaxy-0.1.9.dist-info/RECORD
