Metadata-Version: 2.1
Name: dflow-galaxy
Version: 0.1.9
Summary: 
Author: weihong.xu
Author-email: xuweihong.cn@gmail.com
Requires-Python: >=3.9,<4.0
Classifier: Programming Language :: Python :: 3
Classifier: Programming Language :: Python :: 3.9
Classifier: Programming Language :: Python :: 3.10
Classifier: Programming Language :: Python :: 3.11
Classifier: Programming Language :: Python :: 3.12
Requires-Dist: ai2-kit (==0.18.3)
Requires-Dist: cp2kdata (>=0.6.6,<0.7.0)
Requires-Dist: dp-launching-sdk (>=0.12.0,<0.13.0)
Requires-Dist: dpdispatcher (>=0.6.4,<0.7.0)
Requires-Dist: lbg (>=1.2.24,<2.0.0)
Requires-Dist: pydflow (==1.8.60)
